vinal/__init__.py
vinal/algorithms.py
vinal/build.py
vinal/plot.py
vinal/resources/__init__.py
vinal/resources/constants.js
vinal/resources/plot_create.js
vinal/resources/plot_graph_iterations.js
vinal-0.0.7.dist-info/licenses/LICENSE
vinal-0.0.7.dist-info/METADATA
vinal-0.0.7.dist-info/WHEEL
vinal-0.0.7.dist-info/top_level.txt
vinal-0.0.7.dist-info/RECORD
