Metadata-Version: 2.4
Name: vinal
Version: 0.0.7
Summary: A Python package for visualizing graph algorithms.
Home-page: https://github.com/henryrobbins/tmp.git
Author: Henry Robbins
Author-email: hw.robbins@gmail.com
License: Creative Commons Attribution-NonCommercial-ShareAlike 4.0. https://creativecommons.org/licenses/by-nc-sa/4.0/
Classifier: Programming Language :: Python :: 3.8
Classifier: Programming Language :: Python :: 3.9
Classifier: Programming Language :: Python :: 3.10
Classifier: Operating System :: OS Independent
Requires-Python: >=3.8
License-File: LICENSE
Requires-Dist: numpy>=1.19
Requires-Dist: pandas>=1.2
Requires-Dist: networkx>=3
Requires-Dist: bokeh>=3
Requires-Dist: typing>=3.7
Dynamic: author
Dynamic: author-email
Dynamic: classifier
Dynamic: description
Dynamic: description-content-type
Dynamic: home-page
Dynamic: license
Dynamic: license-file
Dynamic: requires-dist
Dynamic: requires-python
Dynamic: summary
